slackpm
