Metadata-Version: 2.1
Name: slackpm
Version: 0.0.2
Summary: This is a simple script to send push message to Slack channels using Webhooks URL with Slack Apps.
Home-page: https://github.com/mukherjeearnab/slackpm
Author: Arnab Mukherjee
Author-email: mukherjeearnab.arc@gmail.com
License: UNKNOWN
Platform: UNKNOWN
Classifier: Programming Language :: Python :: 3
Classifier: License :: OSI Approved :: MIT License
Classifier: Operating System :: OS Independent
Requires-Python: >=3.6
